Mconfig/__init__.py
Mconfig/core.py
Mconfig/main.py
Mconfig/mconfig.py
Mconfig/yapf/__init__.py
Mconfig/yapf/__main__.py
Mconfig/yapf/yapflib/__init__.py
Mconfig/yapf/yapflib/blank_line_calculator.py
Mconfig/yapf/yapflib/comment_splicer.py
Mconfig/yapf/yapflib/continuation_splicer.py
Mconfig/yapf/yapflib/errors.py
Mconfig/yapf/yapflib/file_resources.py
Mconfig/yapf/yapflib/format_decision_state.py
Mconfig/yapf/yapflib/format_token.py
Mconfig/yapf/yapflib/identify_container.py
Mconfig/yapf/yapflib/line_joiner.py
Mconfig/yapf/yapflib/object_state.py
Mconfig/yapf/yapflib/py3compat.py
Mconfig/yapf/yapflib/pytree_unwrapper.py
Mconfig/yapf/yapflib/pytree_utils.py
Mconfig/yapf/yapflib/pytree_visitor.py
Mconfig/yapf/yapflib/reformatter.py
Mconfig/yapf/yapflib/split_penalty.py
Mconfig/yapf/yapflib/style.py
Mconfig/yapf/yapflib/subtype_assigner.py
Mconfig/yapf/yapflib/unwrapped_line.py
Mconfig/yapf/yapflib/verifier.py
Mconfig/yapf/yapflib/yapf_api.py
Mconfig-1.1.5.dist-info/LICENSE
Mconfig-1.1.5.dist-info/METADATA
Mconfig-1.1.5.dist-info/WHEEL
Mconfig-1.1.5.dist-info/top_level.txt
Mconfig-1.1.5.dist-info/RECORD
