Metadata-Version: 2.1
Name: Mconfig
Version: 1.1.5
Summary: .py 配置文件！Python最好用的配置文件！
Home-page: https://github.com/EVA-JianJun/Mconfig
Author: jianjun
Author-email: 910667956@qq.com
License-File: LICENSE
